amd_taichi/main.py
amd_taichi-1.0.0.dist-info/METADATA
amd_taichi-1.0.0.dist-info/WHEEL
amd_taichi-1.0.0.dist-info/top_level.txt
amd_taichi-1.0.0.dist-info/RECORD
